dmichaels_utils/argv.py
dmichaels_utils/aws/codebuild/utils.py
dmichaels_utils/aws_ecs.py
dmichaels_utils/aws_env.install.bash
dmichaels_utils/aws_env.py
dmichaels_utils/aws_env.sh
dmichaels_utils/aws_url_accounting.py
dmichaels_utils/aws_url_accounting_uniques.py
dmichaels_utils/backup/hms_config_backup.py
dmichaels_utils/chars.py
dmichaels_utils/cli/crypt_cli.py
dmichaels_utils/config/READmE
dmichaels_utils/config/config.py
dmichaels_utils/config/config_basic.py
dmichaels_utils/config/config_cli.py
dmichaels_utils/config/config_cli.sh
dmichaels_utils/config/config_output.py
dmichaels_utils/config/config_with_aws_macros.py
dmichaels_utils/config/config_with_secrets.py
dmichaels_utils/crypt_utils.py
dmichaels_utils/datetime_utils.py
dmichaels_utils/dbmi/portal_envs.py
dmichaels_utils/dev/es-results.py
dmichaels_utils/dev/recent_files_summary.py
dmichaels_utils/dev/recent_files_summary_old.py
dmichaels_utils/dev/recent_released_files.py
dmichaels_utils/dev/work.py
dmichaels_utils/dictionary_parented.py
dmichaels_utils/dictionary_print_utils.py
dmichaels_utils/dictionary_utils.py
dmichaels_utils/elasticsearch_utils.py
dmichaels_utils/env_utils.py
dmichaels_utils/github_utils.py
dmichaels_utils/hms_config.py
dmichaels_utils/hms_config.sh
dmichaels_utils/iterm/iterm_json_component.py
dmichaels_utils/iterm/iterm_utc_clock.py
dmichaels_utils/iterm/iterm_utils.py
dmichaels_utils/misc_utils.py
dmichaels_utils/path_utils.py
dmichaels_utils/portal/indexing_status.py
dmichaels_utils/portal/oneoff/check_for_duplicate_md5sum.py
dmichaels_utils/portal/oneoff/portal_add_consortia_to_items.py
dmichaels_utils/portal/oneoff/portal_items_without_consortia.py
dmichaels_utils/portal/oneoff/portal_permissions_debugging.py
dmichaels_utils/portal/oneoff/portal_submitted_file_summary.py
dmichaels_utils/portal/oneoff/randomize_md5sum_values.py
dmichaels_utils/portal/oneoff/sanity_check_smaht_users_spreadsheet.py
dmichaels_utils/portal/portal_envs.py
dmichaels_utils/portal/portal_files.py
dmichaels_utils-1.1.2.dist-info/LICENSE.txt
dmichaels_utils-1.1.2.dist-info/METADATA
dmichaels_utils-1.1.2.dist-info/WHEEL
dmichaels_utils-1.1.2.dist-info/entry_points.txt
dmichaels_utils-1.1.2.dist-info/RECORD
