Metadata-Version: 2.1
Name: dmichaels-utils
Version: 1.1.2
Summary: Miscellaneous Python utilities from HMS DBMI
Home-page: https://github.com/smaht-dac/dmichaels-utils
License: MIT
Author: Davd Michaels
Author-email: david_michaels@4hms.harvard.deu
Requires-Python: >=3.9,<3.13
Classifier: License :: OSI Approved :: MIT License
Classifier: Programming Language :: Python :: 3
Classifier: Programming Language :: Python :: 3.9
Classifier: Programming Language :: Python :: 3.10
Classifier: Programming Language :: Python :: 3.11
Classifier: Programming Language :: Python :: 3.12
Requires-Dist: boto3 (>=1.35.22,<2.0.0)
Requires-Dist: botocore (>=1.35.14,<2.0.0)
Requires-Dist: dcicutils (>=8.16.4,<9.0.0)
Requires-Dist: importlib (>=1.0.4,<2.0.0)
Requires-Dist: passlib (>=1.7.4,<2.0.0)
Requires-Dist: prettytable (>=3.12.0,<4.0.0)
Requires-Dist: requests (>=2.23.2,<3.0.0)
Requires-Dist: termcolor (>=2.4.0,<3.0.0)
Project-URL: Documentation, https://github.com/smaht-dac/dmichaels-utils
Project-URL: Repository, https://github.com/smaht-dac/dmichaels-utils.git
